{"stats":{"minecraft:killed_by":{"minecraft:player":7},"minecraft:custom":{"minecraft:jump":52,"minecraft:time_since_rest":212,"minecraft:leave_game":1,"minecraft:damage_dealt":7,"minecraft:crouch_one_cm":3823,"minecraft:deaths":7,"minecraft:sprint_one_cm":6964,"minecraft:play_time":2727,"minecraft:damage_taken":2062,"minecraft:time_since_death":178,"minecraft:walk_one_cm":3133,"minecraft:sneak_time":686,"minecraft:total_world_time":2727,"minecraft:fall_one_cm":1254,"minecraft:fly_one_cm":9226}},"DataVersion":3463}